symagen-0.1.0.dist-info/METADATA
symagen-0.1.0.dist-info/WHEEL
symagen/__init__.py
symagen/symagen.abi3.so
symagen-0.1.0.dist-info/RECORD
